paratest_nunit/__init__.py
paratest_nunit/nunit.py
paratest_nunit-0.0.1.dist-info/DESCRIPTION.rst
paratest_nunit-0.0.1.dist-info/METADATA
paratest_nunit-0.0.1.dist-info/RECORD
paratest_nunit-0.0.1.dist-info/WHEEL
paratest_nunit-0.0.1.dist-info/entry_points.txt
paratest_nunit-0.0.1.dist-info/metadata.json
paratest_nunit-0.0.1.dist-info/top_level.txt
